biblioteca_grafos/__init__.py
biblioteca_grafos/grafo.py
testes/__init__.py
testes/teste_minha_classe.py
biblioteca_grafos-0.2.dist-info/METADATA
biblioteca_grafos-0.2.dist-info/WHEEL
biblioteca_grafos-0.2.dist-info/top_level.txt
biblioteca_grafos-0.2.dist-info/RECORD
